pigpio_encoder/__init__.py
pigpio_encoder/pigpio_encoder.py
pigpio_encoder-0.2.1.dist-info/LICENCE.txt
pigpio_encoder-0.2.1.dist-info/METADATA
pigpio_encoder-0.2.1.dist-info/WHEEL
pigpio_encoder-0.2.1.dist-info/top_level.txt
pigpio_encoder-0.2.1.dist-info/RECORD
