Metadata-Version: 2.1
Name: pigpio-encoder
Version: 0.2.1
Summary: Python module for for quickly interface a KY040 rotary encoder with Raspberry Pi.
Home-page: https://github.com/vash3d/pigpio_encoder
Author: vash
Author-email: vash.3d@gmail.com
License: GNU GPLv3
Keywords: rotary encoder switch ky040 gpio raspberry
Platform: UNKNOWN
Classifier: Development Status :: 4 - Beta
Classifier: License :: OSI Approved :: GNU General Public License v3 or later (GPLv3+)
Classifier: Programming Language :: Python :: 3
Classifier: Topic :: Software Development :: Libraries
